asgi_compression/__init__.py
asgi_compression/base.py
asgi_compression/brotli.py
asgi_compression/gzip.py
asgi_compression/identity.py
asgi_compression/middleware.py
asgi_compression/py.typed
asgi_compression/types.py
asgi_compression/zstd.py
asgi_compression-0.1.1.dist-info/licenses/LICENSE
asgi_compression-0.1.1.dist-info/METADATA
asgi_compression-0.1.1.dist-info/WHEEL
asgi_compression-0.1.1.dist-info/top_level.txt
asgi_compression-0.1.1.dist-info/RECORD
