Metadata-Version: 2.4
Name: asgi-compression
Version: 0.1.1
Summary: A framework-independent compression middleware for ASGI applications
Author-email: Serhii Shevchuk <serhii.shevchuk.dev@gmail.com>
Maintainer-email: Serhii Shevchuk <serhii.shevchuk.dev@gmail.com>
License: MIT
Project-URL: Documentation, https://github.com/serozhenka/asgi-compression
Project-URL: Issues, https://github.com/serozhenka/asgi-compression/issues
Project-URL: Source, https://github.com/serozhenka/asgi-compression
Keywords: asgi,compression,middleware,gzip,brotli,zstandard,zstd
Classifier: Development Status :: 4 - Beta
Classifier: Environment :: Web Environment
Classifier: Framework :: AsyncIO
Classifier: Intended Audience :: Developers
Classifier: License :: OSI Approved :: MIT License
Classifier: Operating System :: OS Independent
Classifier: Programming Language :: Python :: 3
Classifier: Programming Language :: Python :: 3.9
Classifier: Programming Language :: Python :: 3.10
Classifier: Programming Language :: Python :: 3.11
Classifier: Programming Language :: Python :: 3.12
Classifier: Programming Language :: Python :: 3.13
Classifier: Programming Language :: Python :: Implementation :: CPython
Classifier: Topic :: Internet :: WWW/HTTP
Classifier: Topic :: Internet :: WWW/HTTP :: HTTP Servers
Classifier: Topic :: Software Development :: Libraries :: Python Modules
Classifier: Typing :: Typed
Requires-Python: >=3.9
License-File: LICENSE
Requires-Dist: multidict>=6.2.0
Provides-Extra: all
Requires-Dist: brotli>=1.1.0; extra == "all"
Requires-Dist: zstandard>=0.23.0; extra == "all"
Provides-Extra: br
Requires-Dist: brotli>=1.1.0; extra == "br"
Provides-Extra: zstd
Requires-Dist: zstandard>=0.23.0; extra == "zstd"
Dynamic: license-file
